autoslot.py
autoslot-2021.10.1.dist-info/LICENSE
autoslot-2021.10.1.dist-info/WHEEL
autoslot-2021.10.1.dist-info/METADATA
autoslot-2021.10.1.dist-info/RECORD
