Metadata-Version: 1.1
Name: autoslot
Version: 2021.10.1
Summary: Classes and metaclasses for easier ``__slots__`` handling.  
Home-page: http://pythonomicon.com
Author: Caleb Hattingh
Author-email: caleb.hattingh@gmail.com
